CHANGELOG.rst
LICENSE
MANIFEST.in
README.rst
ez_setup.py
setup.cfg
setup.py
admin/debian-dupload-hunch.se.conf
admin/dist-base.sh
admin/dist-debian.sh
admin/docsdist.sh
admin/sdist.sh
admin/test-working-copy
admin/old_examples/mvc_process.py
admin/old_examples/html/app/__init__.py
admin/old_examples/html/app/controllers.py
admin/old_examples/html/app/models.py
admin/old_examples/html/config/lighttpd.conf
admin/old_examples/html/public/favicon.ico
admin/old_examples/html/templates/__call__.html
admin/old_examples/html/templates/__call__.json
admin/old_examples/html/templates/__call__.xml
admin/old_examples/html/templates/errors/404.html
admin/old_examples/html/templates/posts/__call__.xml
admin/old_examples/modload/lighttpd.conf
admin/old_examples/modload/app/__init__.py
admin/old_examples/modload/app/controllers.py
admin/old_examples/modload/app/models.py
admin/old_examples/testbed/README
admin/old_examples/testbed/lighttpd.conf
admin/old_examples/testbed/process.py
admin/old_examples/testbed/config/application.py
admin/old_examples/testbed/config/development.py
admin/old_examples/testbed/config/lighttpd.conf
admin/old_examples/testbed/config/production.py
admin/old_examples/testbed/controllers/__init__.py
admin/old_examples/testbed/controllers/resources.py
admin/old_examples/testbed/models/__init__.py
admin/old_examples/testbed/public/favicon.ico
admin/old_examples/testbed/scripts/run-debug.sh
admin/old_examples/testbed/views/_footer.html
admin/old_examples/testbed/views/_header.html
admin/old_examples/testbed/views/index.html
admin/old_examples/testbed/views/mockup.html
admin/old_examples/testbed/views/errors/404.html
admin/old_examples/testbed/views/posts/_post.html
admin/old_examples/testbed/views/posts/index.html
admin/old_examples/testbed/views/posts/show.html
debug/functions.sh
debug/log_usage.sh
docs/etc/300-multiple-choices.html
docs/etc/developing-on-debian.rst
docs/etc/distprocess-debian.sh
docs/etc/distprocess.sh
docs/etc/server_envs.py
lib/smisk.egg-info/PKG-INFO
lib/smisk.egg-info/SOURCES.txt
lib/smisk.egg-info/dependency_links.txt
lib/smisk.egg-info/not-zip-safe
lib/smisk.egg-info/requires.txt
lib/smisk.egg-info/top_level.txt
