Metadata-Version: 1.0
Name: smisk
Version: 1.1.6
Summary: High-performance web service framework
Home-page: http://python-smisk.org/
Author: Rasmus Andersson
Author-email: rasmus@flajm.com
License: Copyright (c) 2007-2009 Rasmus Andersson
